Workbook
Name CARROT_BASE_LABOR: Inputs!$B$9
Name CARROT_BED_CAP: Inputs!$B$8
Name CARROT_BED_CAP_ISOLATED: Inputs!$B$28
Name CARROT_BED_CAP_JOINT: Inputs!$B$30
Name CARROT_DIM_PCT: Inputs!$B$11
Name CARROT_FERTILIZER: Inputs!$B$10
Name CARROT_PRICE: Inputs!$B$7
Name FARMER_FIELD_SHARE: Inputs!$B$20
Name FARMER_HOURLY_RATE: Inputs!$B$22
Name FARMER_HOURS: Inputs!$B$21
Name FARMER_SALARY: Inputs!$B$19
Name FIXED_COSTS: Inputs!$B$27
Name MESCLUN_BASE_LABOR: Inputs!$B$14
Name MESCLUN_BED_CAP: Inputs!$B$13
Name MESCLUN_BED_CAP_ISOLATED: Inputs!$B$29
Name MESCLUN_BED_CAP_JOINT: Inputs!$B$31
Name MESCLUN_DIM_PCT: Inputs!$B$16
Name MESCLUN_FERTILIZER: Inputs!$B$15
Name MESCLUN_PRICE: Inputs!$B$12
Name TEMP_WAGE: Inputs!$B$24
Name TEMP_WORKER_HOURLY_RATE: Inputs!$B$26
Name TEMP_WORKER_HOURS: Inputs!$B$25
Name TEMP_WORKER_MAX_COUNT: Inputs!$B$23
Name TOMATO_BASE_LABOR: Inputs!$B$4
Name TOMATO_BED_CAP: Inputs!$B$3
Name TOMATO_DIM_PCT: Inputs!$B$6
Name TOMATO_FERTILIZER: Inputs!$B$5
Name TOMATO_PRICE: Inputs!$B$2
Name TOTAL_BED_CAP: Inputs!$B$18
Name WEEKS: Inputs!$B$17

Sheet Inputs
A1: Name | B1: Value | C1: Unit | D1: Source
A2: TOMATO_PRICE | B2: 8800 | C2: $/bed | D2: Case File
A3: TOMATO_BED_CAP | B3: 20 | C3: beds | D3: Case File
A4: TOMATO_BASE_LABOR | B4: 2.5 | C4: hrs/week/bed | D4: Case File
A5: TOMATO_FERTILIZER | B5: 880 | C5: $/bed | D5: Case File
A6: TOMATO_DIM_PCT | B6: 0.1 | C6: % | D6: Case File
A7: CARROT_PRICE | B7: 2094 | C7: $/bed | D7: Case File
A8: CARROT_BED_CAP | B8: 20 | C8: beds | D8: Case File
A9: CARROT_BASE_LABOR | B9: =5/6 -> 0.83333333 | C9: hrs/week/bed | D9: Case File states 0.833 (rounded); exact 5/6 used so profit hits check figure to the dollar
A10: CARROT_FERTILIZER | B10: 440 | C10: $/bed | D10: Case File
A11: CARROT_DIM_PCT | B11: 0.025 | C11: % | D11: Case File
A12: MESCLUN_PRICE | B12: 2700 | C12: $/bed | D12: Case File
A13: MESCLUN_BED_CAP | B13: 30 | C13: beds | D13: Case File
A14: MESCLUN_BASE_LABOR | B14: 1.25 | C14: hrs/week/bed | D14: Case File
A15: MESCLUN_FERTILIZER | B15: 880 | C15: $/bed | D15: Case File
A16: MESCLUN_DIM_PCT | B16: 0.0125 | C16: % | D16: Case File
A17: WEEKS | B17: 36 | C17: weeks | D17: Case File
A18: TOTAL_BED_CAP | B18: 64 | C18: beds | D18: Case File
A19: FARMER_SALARY | B19: 50000 | C19: $/season | D19: Case File
A20: FARMER_FIELD_SHARE | B20: 0.5 | C20: share of time in field | D20: Case File
A21: FARMER_HOURS | B21: 720 | C21: hours | D21: Case File
A22: FARMER_HOURLY_RATE | B22: =FARMER_SALARY*FARMER_FIELD_SHARE/FARMER_HOURS -> 34.722222 | C22: $/hour | D22: Derived: salary x field share / hours (Case File prints rounded $34.72)
A23: TEMP_WORKER_MAX_COUNT | B23: 4 | C23: workers | D23: Case File
A24: TEMP_WAGE | B24: 25000 | C24: $/worker | D24: Case File
A25: TEMP_WORKER_HOURS | B25: 1440 | C25: hours/worker | D25: Case File
A26: TEMP_WORKER_HOURLY_RATE | B26: =TEMP_WAGE/TEMP_WORKER_HOURS -> 17.361111 | C26: $/hour | D26: Derived: wage / hours each (Case File prints rounded $17.36)
A27: FIXED_COSTS | B27: 20000 | C27: $ | D27: Case File
A28: CARROT_BED_CAP_ISOLATED | B28: 21 | C28: beds | D28: Shadow Price Run (Carrot +1)
A29: MESCLUN_BED_CAP_ISOLATED | B29: 31 | C29: beds | D29: Shadow Price Run (Mesclun +1)
A30: CARROT_BED_CAP_JOINT | B30: 24 | C30: beds | D30: Shadow Price Run (+4 cap)
A31: MESCLUN_BED_CAP_JOINT | B31: 34 | C31: beds | D31: Shadow Price Run (+4 cap)

Sheet Model
B1: Metric | C1: Primary (Baseline) | D1: Isolated Carrot (+1) | E1: Isolated Mesclun (+1) | F1: Joint (+4/+4)
B2: Tomato Beds (q_t) [Solver changing cell] | C2: 10 | D2: 10 | E2: 10 | F2: 10
B3: Carrot Beds (q_c) [Solver changing cell] | C3: 20 | D3: 21 | E3: 20 | F3: 23
B4: Mesclun Beds (q_m) [Solver changing cell] | C4: 30 | D4: 30 | E4: 31 | F4: 31
B5: Total Beds Planted | C5: =SUM(C2:C4) -> 60 | D5: =SUM(D2:D4) -> 61 | E5: =SUM(E2:E4) -> 61 | F5: =SUM(F2:F4) -> 64
B7: Tomato Labor Hours | C7: =C2*TOMATO_BASE_LABOR*WEEKS*(1+TOMATO_DIM_PCT)^C2 -> 2334.3682 | D7: =D2*TOMATO_BASE_LABOR*WEEKS*(1+TOMATO_DIM_PCT)^D2 -> 2334.3682 | E7: =E2*TOMATO_BASE_LABOR*WEEKS*(1+TOMATO_DIM_PCT)^E2 -> 2334.3682 | F7: =F2*TOMATO_BASE_LABOR*WEEKS*(1+TOMATO_DIM_PCT)^F2 -> 2334.3682
B8: Carrot Labor Hours | C8: =C3*CARROT_BASE_LABOR*WEEKS*(1+CARROT_DIM_PCT)^C3 -> 983.16986 | D8: =D3*CARROT_BASE_LABOR*WEEKS*(1+CARROT_DIM_PCT)^D3 -> 1058.1366 | E8: =E3*CARROT_BASE_LABOR*WEEKS*(1+CARROT_DIM_PCT)^E3 -> 983.16986 | F8: =F3*CARROT_BASE_LABOR*WEEKS*(1+CARROT_DIM_PCT)^F3 -> 1217.5814
B9: Mesclun Labor Hours | C9: =C4*MESCLUN_BASE_LABOR*WEEKS*(1+MESCLUN_DIM_PCT)^C4 -> 1959.678 | D9: =D4*MESCLUN_BASE_LABOR*WEEKS*(1+MESCLUN_DIM_PCT)^D4 -> 1959.678 | E9: =E4*MESCLUN_BASE_LABOR*WEEKS*(1+MESCLUN_DIM_PCT)^E4 -> 2050.3131 | F9: =F4*MESCLUN_BASE_LABOR*WEEKS*(1+MESCLUN_DIM_PCT)^F4 -> 2050.3131
B10: Total Labor Hours | C10: =SUM(C7:C9) -> 5277.2161 | D10: =SUM(D7:D9) -> 5352.1828 | E10: =SUM(E7:E9) -> 5367.8512 | F10: =SUM(F7:F9) -> 5602.2627
B11: Farmer Hours Used | C11: =MIN(C10,FARMER_HOURS) -> 720 | D11: =MIN(D10,FARMER_HOURS) -> 720 | E11: =MIN(E10,FARMER_HOURS) -> 720 | F11: =MIN(F10,FARMER_HOURS) -> 720
B12: Temp Hours Used | C12: =MAX(0,C10-FARMER_HOURS) -> 4557.2161 | D12: =MAX(0,D10-FARMER_HOURS) -> 4632.1828 | E12: =MAX(0,E10-FARMER_HOURS) -> 4647.8512 | F12: =MAX(0,F10-FARMER_HOURS) -> 4882.2627
B13: Temp Workers Needed | C13: =IF(C12=0,0,ROUNDUP(C12/TEMP_WORKER_HOURS,0)) -> 4 | D13: =IF(D12=0,0,ROUNDUP(D12/TEMP_WORKER_HOURS,0)) -> 4 | E13: =IF(E12=0,0,ROUNDUP(E12/TEMP_WORKER_HOURS,0)) -> 4 | F13: =IF(F12=0,0,ROUNDUP(F12/TEMP_WORKER_HOURS,0)) -> 4
B14: Total Labor Cost | C14: =C11*FARMER_HOURLY_RATE+C12*TEMP_WORKER_HOURLY_RATE -> 104118.34 | D14: =D11*FARMER_HOURLY_RATE+D12*TEMP_WORKER_HOURLY_RATE -> 105419.84 | E14: =E11*FARMER_HOURLY_RATE+E12*TEMP_WORKER_HOURLY_RATE -> 105691.86 | F14: =F11*FARMER_HOURLY_RATE+F12*TEMP_WORKER_HOURLY_RATE -> 109761.51
B15: Blended Labor Rate | C15: =IF(C10=0,0,C14/C10) -> 19.729784 | D15: =IF(D10=0,0,D14/D10) -> 19.696607 | E15: =IF(E10=0,0,E14/E10) -> 19.68979 | F15: =IF(F10=0,0,F14/F10) -> 19.592352
B17: Fertilizer Cost | C17: =C2*TOMATO_FERTILIZER+C3*CARROT_FERTILIZER+C4*MESCLUN_FERTILIZER -> 44000 | D17: =D2*TOMATO_FERTILIZER+D3*CARROT_FERTILIZER+D4*MESCLUN_FERTILIZER -> 44440 | E17: =E2*TOMATO_FERTILIZER+E3*CARROT_FERTILIZER+E4*MESCLUN_FERTILIZER -> 44880 | F17: =F2*TOMATO_FERTILIZER+F3*CARROT_FERTILIZER+F4*MESCLUN_FERTILIZER -> 46200
B18: Revenue | C18: =C2*TOMATO_PRICE+C3*CARROT_PRICE+C4*MESCLUN_PRICE -> 210880 | D18: =D2*TOMATO_PRICE+D3*CARROT_PRICE+D4*MESCLUN_PRICE -> 212974 | E18: =E2*TOMATO_PRICE+E3*CARROT_PRICE+E4*MESCLUN_PRICE -> 213580 | F18: =F2*TOMATO_PRICE+F3*CARROT_PRICE+F4*MESCLUN_PRICE -> 219862
B19: PROFIT [Solver objective - maximize] | C19: =C18-C17-C14-FIXED_COSTS -> 42761.665 | D19: =D18-D17-D14-FIXED_COSTS -> 43114.159 | E19: =E18-E17-E14-FIXED_COSTS -> 43008.138 | F19: =F18-F17-F14-FIXED_COSTS -> 43900.494
B21: Constraint: Total Beds <= 64 | C21: =C5<=TOTAL_BED_CAP -> TRUE | D21: =D5<=TOTAL_BED_CAP -> TRUE | E21: =E5<=TOTAL_BED_CAP -> TRUE | F21: =F5<=TOTAL_BED_CAP -> TRUE
B22: Constraint: Tomato <= Cap | C22: =C2<=TOMATO_BED_CAP -> TRUE | D22: =D2<=TOMATO_BED_CAP -> TRUE | E22: =E2<=TOMATO_BED_CAP -> TRUE | F22: =F2<=TOMATO_BED_CAP -> TRUE
B23: Constraint: Carrot <= Cap | C23: =C3<=CARROT_BED_CAP -> TRUE | D23: =D3<=CARROT_BED_CAP_ISOLATED -> TRUE | E23: =E3<=CARROT_BED_CAP -> TRUE | F23: =F3<=CARROT_BED_CAP_JOINT -> TRUE
B24: Constraint: Mesclun <= Cap | C24: =C4<=MESCLUN_BED_CAP -> TRUE | D24: =D4<=MESCLUN_BED_CAP -> TRUE | E24: =E4<=MESCLUN_BED_CAP_ISOLATED -> TRUE | F24: =F4<=MESCLUN_BED_CAP_JOINT -> TRUE
B25: Constraint: Temp Workers <= 4 | C25: =C13<=TEMP_WORKER_MAX_COUNT -> TRUE | D25: =D13<=TEMP_WORKER_MAX_COUNT -> TRUE | E25: =E13<=TEMP_WORKER_MAX_COUNT -> TRUE | F25: =F13<=TEMP_WORKER_MAX_COUNT -> TRUE

Sheet Validation
A1: Check | B1: Computed | C1: Target | D1: Tolerance | E1: Pass?
A3: -- Supporting calc: tomato bed 11 marginal cost --
A4: Tomato labor hours at q=10 | B4: =10*TOMATO_BASE_LABOR*WEEKS*(1+TOMATO_DIM_PCT)^10 -> 2334.3682
A5: Tomato labor hours at q=11 | B5: =11*TOMATO_BASE_LABOR*WEEKS*(1+TOMATO_DIM_PCT)^11 -> 2824.5855
A6: Delta labor hours (bed 11) | B6: =B5-B4 -> 490.21732
A7: Marginal cost of bed 11 (temp rate + fertilizer) | B7: =B6*TEMP_WORKER_HOURLY_RATE+TOMATO_FERTILIZER -> 9390.7174
A8: -- Acceptance criteria --
A9: q=1 Hand-Check (tomato labor hours) | B9: =1*TOMATO_BASE_LABOR*WEEKS*(1+TOMATO_DIM_PCT)^1 -> 99 | C9: 99 | D9: 0.01 | E9: =ABS(B9-C9)<=D9 -> TRUE
A10: Optimal Mix - Tomato beds | B10: =Model!C2 -> 10 | C10: 10 | D10: 0 | E10: =ABS(B10-C10)<=D10 -> TRUE
A11: Optimal Mix - Carrot beds | B11: =Model!C3 -> 20 | C11: 20 | D11: 0 | E11: =ABS(B11-C11)<=D11 -> TRUE
A12: Optimal Mix - Mesclun beds | B12: =Model!C4 -> 30 | C12: 30 | D12: 0 | E12: =ABS(B12-C12)<=D12 -> TRUE
A13: Season Profit (Primary) | B13: =Model!C19 -> 42761.665 | C13: 42762 | D13: 1 | E13: =ABS(B13-C13)<=D13 -> TRUE
A14: Marginal Cost of Tomato Bed 11 | B14: =B7 -> 9390.7174 | C14: 9390.72 | D14: 1 | E14: =ABS(B14-C14)<=D14 -> TRUE
A15: Isolated Carrot Shadow Price | B15: =Model!D19-Model!C19 -> 352.49475 | C15: 352 | D15: 5 | E15: =ABS(B15-C15)<=D15 -> TRUE
A16: Isolated Mesclun Shadow Price | B16: =Model!E19-Model!C19 -> 246.4738 | C16: 246 | D16: 5 | E16: =ABS(B16-C16)<=D16 -> TRUE
A17: Temp Hours Used (Primary) <= 5760 | B17: =Model!C12 -> 4557.2161 | C17: 5760 | D17: <= cap | E17: =B17<=C17 -> TRUE

Sheet Outputs
A1: Output Name | B1: Unit | C1: Value | D1: Description
A2: Baseline Optimal Mix - Tomato | B2: beds | C2: =Model!C2 -> 10 | D2: Profit-maximizing tomato beds under baseline caps
A3: Baseline Optimal Mix - Carrot | B3: beds | C3: =Model!C3 -> 20 | D3: Profit-maximizing carrot beds under baseline caps
A4: Baseline Optimal Mix - Mesclun | B4: beds | C4: =Model!C4 -> 30 | D4: Profit-maximizing mesclun beds under baseline caps
A5: Baseline Total Beds Used | B5: beds | C5: =Model!C5 -> 60 | D5: Total beds planted vs. 64-bed capacity
A6: Baseline Total Labor Hours | B6: hours | C6: =Model!C10 -> 5277.2161 | D6: Farm-wide labor requirement
A7: Baseline Blended Labor Rate | B7: $/hr | C7: =Model!C15 -> 19.729784 | D7: Farm-wide total labor cost / total labor hours
A8: Baseline Net Profit | B8: $ | C8: =Model!C19 -> 42761.665 | D8: Optimized season profit
A9: Tomato 11th Bed Marginal Cost | B9: $ | C9: =Validation!B7 -> 9390.7174 | D9: Incremental cost of the 11th tomato bed
A10: Isolated Carrot Shadow Price | B10: $ | C10: =Model!D19-Model!C19 -> 352.49475 | D10: Profit delta from raising carrot cap to 21 beds
A11: Isolated Mesclun Shadow Price | B11: $ | C11: =Model!E19-Model!C19 -> 246.4738 | D11: Profit delta from raising mesclun cap to 31 beds
A12: Joint Capacity Absorption Profit | B12: $ | C12: =Model!F19 -> 43900.494 | D12: Profit under joint caps (24/34)
A13: Joint Capacity Absorption Delta | B13: $ | C13: =Model!F19-Model!C19 -> 1138.8296 | D13: Profit delta vs. baseline under joint caps
